promising_stocks/__init__.py
promising_stocks/main.py
promising_stocks-0.2.6.dist-info/LICENSE
promising_stocks-0.2.6.dist-info/METADATA
promising_stocks-0.2.6.dist-info/WHEEL
promising_stocks-0.2.6.dist-info/top_level.txt
promising_stocks-0.2.6.dist-info/RECORD
